LICENSE
MANIFEST.in
README.rst
requirements.txt
setup.py
django_herokuify.egg-info/PKG-INFO
django_herokuify.egg-info/SOURCES.txt
django_herokuify.egg-info/dependency_links.txt
django_herokuify.egg-info/requires.txt
django_herokuify.egg-info/top_level.txt
docs/Makefile
docs/aws.rst
docs/cache.rst
docs/common.rst
docs/conf.py
docs/db.rst
docs/index.rst
docs/mail.rst
docs/make.bat
docs/storage.rst
docs/_static/github.png
docs/_static/page_edit.png
docs/_static/twitter.png
docs/_templates/editdocument.html
docs/_templates/page.html
docs/_templates/quicklinks.html
herokuify/__init__.py
herokuify/aws.py
herokuify/cache.py
herokuify/common.py
herokuify/db.py
herokuify/storage.py
herokuify/mail/__init__.py
herokuify/mail/mailgun.py
herokuify/mail/sendgrid.py