Metadata-Version: 1.1
Name: django-herokuify
Version: 1.0.pre3
Summary: Automatic Django configuration and utilities for Heroku.
Home-page: https://github.com/nigma/django-herokuify
Author: Filip Wasilewski
Author-email: en@ig.ma
License: BSD
Download-URL: https://github.com/nigma/django-herokuify/zipball/master
Platform: UNKNOWN
Classifier: Development Status :: 4 - Beta
Classifier: Environment :: Web Environment
Classifier: Framework :: Django
Classifier: Intended Audience :: Developers
Classifier: License :: OSI Approved :: BSD License
Classifier: Operating System :: OS Independent
Classifier: Programming Language :: Python
Classifier: Programming Language :: Python :: 2.6
Classifier: Programming Language :: Python :: 2.7
Classifier: Topic :: Software Development :: Libraries :: Python Modules
